focused_unittest.py
focused_unittest-0.1.1.dist-info/LICENSE
focused_unittest-0.1.1.dist-info/METADATA
focused_unittest-0.1.1.dist-info/WHEEL
focused_unittest-0.1.1.dist-info/top_level.txt
focused_unittest-0.1.1.dist-info/RECORD
