Metadata-Version: 2.1
Name: focused_unittest
Version: 0.1.1
Summary: Decorator to select only one unit test to be run.
Home-page: https://github.com/barsv/focused_unittest
Author: Stan
Author-email: barsv85@gmail.com
Classifier: Programming Language :: Python :: 3
Classifier: License :: OSI Approved :: MIT License
Classifier: Operating System :: OS Independent
Requires-Python: >=3.6
License-File: LICENSE
